craft_api/__init__.py
craft_api/craft_api.py
craft_api-0.1.1.dist-info/METADATA
craft_api-0.1.1.dist-info/WHEEL
craft_api-0.1.1.dist-info/top_level.txt
craft_api-0.1.1.dist-info/RECORD
